ytube_video_downloader/__init__.py
ytube_video_downloader/main.py
ytube_video_downloader-1.0.1.dist-info/LICENSE
ytube_video_downloader-1.0.1.dist-info/METADATA
ytube_video_downloader-1.0.1.dist-info/WHEEL
ytube_video_downloader-1.0.1.dist-info/entry_points.txt
ytube_video_downloader-1.0.1.dist-info/top_level.txt
ytube_video_downloader-1.0.1.dist-info/RECORD
