Metadata-Version: 2.1
Name: ytube-video-downloader
Version: 1.0.1
Summary: YTube-Video-Downloader is a command-line application written in Python that downloads videos from a specific YouTube channel according to given filters.
Home-page: https://github.com/maksr137/ytube-video-downloader
Author: Maksym Remezovskyi
Author-email: maks.remezovskij1@gmail.com
License: MIT
Classifier: Programming Language :: Python :: 3
Classifier: License :: OSI Approved :: MIT License
Classifier: Operating System :: OS Independent
License-File: LICENSE
Requires-Dist: aiohttp (==3.8.1)
Requires-Dist: aiosignal (==1.2.0)
Requires-Dist: async-timeout (==4.0.2)
Requires-Dist: attrs (==22.1.0)
Requires-Dist: cachetools (==5.2.0)
Requires-Dist: certifi (==2022.6.15)
Requires-Dist: charset-normalizer (==2.1.0)
Requires-Dist: fake-useragent (==0.1.11)
Requires-Dist: frozenlist (==1.3.1)
Requires-Dist: google-api-core (==2.8.2)
Requires-Dist: google-api-python-client (==2.57.0)
Requires-Dist: google-auth (==2.10.0)
Requires-Dist: google-auth-httplib2 (==0.1.0)
Requires-Dist: googleapis-common-protos (==1.56.4)
Requires-Dist: httplib2 (==0.20.4)
Requires-Dist: idna (==3.3)
Requires-Dist: multidict (==6.0.2)
Requires-Dist: protobuf (==4.21.5)
Requires-Dist: pyasn1 (==0.4.8)
Requires-Dist: pyasn1-modules (==0.2.8)
Requires-Dist: pyparsing (==3.0.9)
Requires-Dist: requests (==2.28.1)
Requires-Dist: rsa (==4.9)
Requires-Dist: six (==1.16.0)
Requires-Dist: uritemplate (==4.1.1)
Requires-Dist: urllib3 (==1.26.11)
Requires-Dist: yarl (==1.8.1)
